{
	"id": "pf2e-target-damage",
	"title": "PF2e Target Damage",
	"description": "QoL module for improving damage application in Pathfinder 2e.",
	"version": "This is replaced",
	"authors": [
		{
			"name": "MrVauxs",
			"discord": "MrVauxs#8622",
			"twitter": "@ThatVauxs",
			"email": "mrvauxs@gmail.com",
			"ko-fi": "MrVauxs",
			"patreon": "MrVauxs",
			"flags": {}
		}
	],
	"compatibility": {
		"minimum": "10",
		"verified": "11"
	},
	"relationships": {
		"flags": {
			"optional": [
				{
					"id": "df-templates",
					"type": "module",
					"manifest": "https://dragonflagon.cafe/mods/man/df-templates",
					"reason": "Allows you to automatically select targets on template placemenet, speeding up the targeting process for AoEs."
				}
			]
		},
		"optional": [
			{
				"id": "df-templates",
				"type": "module",
				"manifest": "https://dragonflagon.cafe/mods/man/df-templates",
				"reason": "Allows you to automatically select targets on template placemenet, speeding up the targeting process for AoEs."
			}
		],
		"conflicts": [
			{
				"id": "target-lock",
				"type": "module",
				"reason": "PF2e Damage Target is a successor to Target Lock, and borrows a most of its code from it. Target Lock is unmaintained and enabling both modules is not recommended."
			}
		],
		"systems": [
			{
				"id": "pf2e",
				"type": "system",
				"compatibility": {
					"minimum": "4.10.4"
				}
			}
		]
	},
	"socket": true,
	"languages": [
		{
			"lang": "en",
			"name": "English",
			"path": "languages/en.json"
		},
		{
			"lang": "pl",
			"name": "polski",
			"path": "languages/pl.json"
		},
		{
			"lang": "fr",
			"name": "Français",
			"path": "languages/fr.json"
		},
		{
			"lang": "cn",
			"name": "中文（简体）",
			"path": "languages/cn.json"
		},
		{
			"lang": "zh-tw",
			"name": "正體中文",
			"path": "languages/zh-tw.json"
		}
	],
	"media": [
		{
			"type": "setup",
			"name": "Setup Screen",
			"path": "assets/setup.webm"
		}
	],
	"url": "https://github.com/MrVauxs/PF2e-Target-Damage",
	"manifest": "This is replaced",
	"download": "This is replaced",
	"readme": "https://github.com/MrVauxs/PF2e-Target-Damage",
	"bugs": "https://github.com/MrVauxs/PF2e-Target-Damage/issues",
	"changelog": "https://github.com/MrVauxs/PF2e-Target-Damage/blob/master/CHANGELOG.md",
	"esmodules": [
		"module/settings.js",
		"module/target-damage.js"
	],
	"styles": [
		"styles/target-damage.css"
	]
}